CHANGES.txt
MANIFEST.in
README.txt
bootstrap.py
buildout.cfg
setup.py
etc/thumbs_example.ini
src/cykooz/__init__.py
src/cykooz.thumbs.egg-info/PKG-INFO
src/cykooz.thumbs.egg-info/SOURCES.txt
src/cykooz.thumbs.egg-info/dependency_links.txt
src/cykooz.thumbs.egg-info/entry_points.txt
src/cykooz.thumbs.egg-info/namespace_packages.txt
src/cykooz.thumbs.egg-info/not-zip-safe
src/cykooz.thumbs.egg-info/requires.txt
src/cykooz.thumbs.egg-info/top_level.txt
src/cykooz/thumbs/__init__.py
src/cykooz/thumbs/application.py
src/cykooz/thumbs/image_processing.py
src/cykooz/thumbs/middleware.py
src/cykooz/thumbs/tests/__init__.py
src/cykooz/thumbs/tests/image.jpg
src/cykooz/thumbs/tests/index.html
src/cykooz/thumbs/tests/test.py