Metadata-Version: 1.0
Name: cykooz.thumbs
Version: 0.2
Summary: WSGI middleware for image resizing
Home-page: https://bitbucket.org/cykooz/cykooz.thumbs
Author: Cykooz
Author-email: saikuz@mail.ru
License: GPL
Keywords: wsgi middleware imaging
Platform: UNKNOWN
Classifier: Environment :: Web Environment
Classifier: Development Status :: 4 - Beta
Classifier: Intended Audience :: Developers
Classifier: Programming Language :: Python
Classifier: Natural Language :: English
Classifier: Operating System :: OS Independent
Classifier: Topic :: Internet :: WWW/HTTP :: WSGI :: Middleware
Classifier: Topic :: Internet :: WWW/HTTP :: WSGI :: Application
